oops/.coveragerc
oops/__init__.py
oops/_version.py
oops/body.py
oops/config.py
oops/constants.py
oops/event.py
oops/fittable.py
oops/lightsource.py
oops/meshgrid.py
oops/spice_support.py
oops/transform.py
oops/unittester_support.py
oops/utils.py
oops/backplane/__init__.py
oops/backplane/all.py
oops/backplane/ansa.py
oops/backplane/border.py
oops/backplane/distance.py
oops/backplane/lighting.py
oops/backplane/limb.py
oops/backplane/orbit.py
oops/backplane/pixel.py
oops/backplane/pole.py
oops/backplane/resolution.py
oops/backplane/ring.py
oops/backplane/sky.py
oops/backplane/spheroid.py
oops/backplane/where.py
oops/cadence/__init__.py
oops/cadence/cadence_.py
oops/cadence/dualcadence.py
oops/cadence/instant.py
oops/cadence/metronome.py
oops/cadence/reshapedcadence.py
oops/cadence/reversedcadence.py
oops/cadence/sequence.py
oops/cadence/tdicadence.py
oops/calibration/__init__.py
oops/calibration/calibration_.py
oops/calibration/flatcalib.py
oops/calibration/nullcalib.py
oops/calibration/radiance.py
oops/calibration/rawcounts.py
oops/fov/__init__.py
oops/fov/barrelfov.py
oops/fov/flatfov.py
oops/fov/fov_.py
oops/fov/gapfov.py
oops/fov/nullfov.py
oops/fov/offsetfov.py
oops/fov/polynomialfov.py
oops/fov/slicefov.py
oops/fov/subarray.py
oops/fov/subsampledfov.py
oops/fov/tdifov.py
oops/fov/wcsfov.py
oops/frame/__init__.py
oops/frame/cmatrix.py
oops/frame/frame_.py
oops/frame/inclinedframe.py
oops/frame/laplaceframe.py
oops/frame/navigation.py
oops/frame/poleframe.py
oops/frame/postargframe.py
oops/frame/ringframe.py
oops/frame/rotation.py
oops/frame/spiceframe.py
oops/frame/spicetype1frame.py
oops/frame/spinframe.py
oops/frame/synchronousframe.py
oops/frame/trackerframe.py
oops/frame/twovectorframe.py
oops/gold_master/__init__.py
oops/gold_master/all.py
oops/gold_master/ansa.py
oops/gold_master/border.py
oops/gold_master/distance.py
oops/gold_master/lighting.py
oops/gold_master/limb.py
oops/gold_master/orbit.py
oops/gold_master/pole.py
oops/gold_master/resolution.py
rms_oops-0.1.4.dist-info/licenses/LICENSE.md
rms_oops-0.1.4.dist-info/METADATA
rms_oops-0.1.4.dist-info/WHEEL
rms_oops-0.1.4.dist-info/top_level.txt
rms_oops-0.1.4.dist-info/RECORD
