Metadata-Version: 2.4
Name: rms-oops
Version: 0.1.4
Summary: Object-Oriented Python and SPICE
Maintainer-email: "Robert S. French" <rfrench@seti.org>, "Joseph N. Spitale" <jspitale@seti.org>
License: Apache-2.0
Project-URL: Homepage, https://github.com/SETI/rms-oops
Project-URL: Repository, https://github.com/SETI/rms-oops
Project-URL: Source, https://github.com/SETI/rms-oops
Project-URL: Issues, https://github.com/SETI/rms-oops/issues
Keywords: oops
Classifier: Development Status :: 5 - Production/Stable
Classifier: Natural Language :: English
Classifier: Topic :: Scientific/Engineering
Classifier: Topic :: Scientific/Engineering :: Astronomy
Classifier: Topic :: Software Development :: Libraries :: Python Modules
Classifier: Topic :: Utilities
Classifier: License :: OSI Approved :: Apache Software License
Classifier: Programming Language :: Python :: 3.8
Classifier: Programming Language :: Python :: 3.9
Classifier: Programming Language :: Python :: 3.10
Classifier: Programming Language :: Python :: 3.11
Classifier: Programming Language :: Python :: 3.12
Classifier: Programming Language :: Python :: 3.13
Classifier: Operating System :: MacOS :: MacOS X
Classifier: Operating System :: POSIX :: Linux
Classifier: Operating System :: Microsoft :: Windows
Requires-Python: >=3.8
License-File: LICENSE.md
Requires-Dist: astropy
Requires-Dist: cspyce
Requires-Dist: numpy
Requires-Dist: Pillow
Requires-Dist: pyparsing
Requires-Dist: rms-filecache>=2.0.3
Requires-Dist: rms-fpzip
Requires-Dist: rms-interval
Requires-Dist: rms-julian
Requires-Dist: rms-pdsparser
Requires-Dist: rms-pdstable
Requires-Dist: rms-polymath
Requires-Dist: rms-solar
Requires-Dist: rms-tabulation
Requires-Dist: rms-vax
Requires-Dist: rms-vicar
Requires-Dist: scipy
Dynamic: license-file
